LICENSE
README.md
ngrok_flask_cart.py
setup.cfg
setup.py
ngrok_flask_cart.egg-info/PKG-INFO
ngrok_flask_cart.egg-info/SOURCES.txt
ngrok_flask_cart.egg-info/dependency_links.txt
ngrok_flask_cart.egg-info/requires.txt
ngrok_flask_cart.egg-info/top_level.txt