Metadata-Version: 2.1
Name: ngrok-flask-cart
Version: 0.0.7
Summary: An offshoot of flask-ngrok for demo Flask apps using ngrok.
Home-page: UNKNOWN
Author: Nathan Reitinger
License: UNKNOWN
Keywords: flask ngrok CART
Platform: UNKNOWN
Classifier: Programming Language :: Python :: 3.6
Classifier: License :: OSI Approved :: Apache Software License
Classifier: Operating System :: OS Independent
License-File: LICENSE
